odoo/addons/widget_list_row_color/README.rst
odoo/addons/widget_list_row_color/__init__.py
odoo/addons/widget_list_row_color/__manifest__.py
odoo/addons/widget_list_row_color/static/description/ejemplo.png
odoo/addons/widget_list_row_color/static/description/icon.png
odoo/addons/widget_list_row_color/static/src/js/list_renderer.js
odoo/addons/widget_list_row_color/views/widget_list_row_color_view.xml
odoo12_addon_widget_list_row_color-12.0.0.1.0.dist-info/METADATA
odoo12_addon_widget_list_row_color-12.0.0.1.0.dist-info/WHEEL
odoo12_addon_widget_list_row_color-12.0.0.1.0.dist-info/top_level.txt
odoo12_addon_widget_list_row_color-12.0.0.1.0.dist-info/RECORD
